COPYING
MANIFEST.in
README.rst
bootstrap-buildout.py
buildout.cfg
requirements.txt
setup.py
version.txt
bob/__init__.py
bob.paper.CVPRW_2016.egg-info/PKG-INFO
bob.paper.CVPRW_2016.egg-info/SOURCES.txt
bob.paper.CVPRW_2016.egg-info/dependency_links.txt
bob.paper.CVPRW_2016.egg-info/entry_points.txt
bob.paper.CVPRW_2016.egg-info/requires.txt
bob.paper.CVPRW_2016.egg-info/top_level.txt
bob/paper/__init__.py
bob/paper/test.py
bob/paper/CVPRW_2016/__init__.py
bob/paper/CVPRW_2016/script/ISV_intuition.py
bob/paper/CVPRW_2016/script/__init__.py
bob/paper/CVPRW_2016/script/generate_plot_results.py
doc/conf.py
doc/guide.rst
doc/index.rst