Metadata-Version: 1.1
Name: bob.paper.CVPRW-2016
Version: 1.0.2
Summary: Running the experiments as given in paper: "Heterogeneous Face Recognition using Inter-Session Variability Modelling".
Home-page: http://gitlab.idiap.ch/
Author: Tiago de Freitas Pereira
Author-email: tiago.pereira@idiap.ch
License: BSD
Keywords: bob
Platform: UNKNOWN
Classifier: Development Status :: 4 - Beta
Classifier: Intended Audience :: Developers
Classifier: License :: OSI Approved :: BSD License
Classifier: Natural Language :: English
Classifier: Programming Language :: Python
Classifier: Topic :: Scientific/Engineering :: Artificial Intelligence
